nr/__init__.py
nr/utils/__init__.py
nr/utils/io/__init__.py
nr/utils/io/py.typed
nr/utils/io/readers.py
nr.utils.io-0.1.1.dist-info/LICENSE.txt
nr.utils.io-0.1.1.dist-info/METADATA
nr.utils.io-0.1.1.dist-info/WHEEL
nr.utils.io-0.1.1.dist-info/top_level.txt
nr.utils.io-0.1.1.dist-info/RECORD
