Metadata-Version: 2.1
Name: nr.utils.io
Version: 0.1.1
Summary: Collection for IO utilities.
Home-page: https://git.niklasrosenstein.com/NiklasRosenstein/nr
Author: Niklas Rosenstein
Author-email: rosensteinniklas@gmail.com
License: MIT
Platform: UNKNOWN
Requires-Python: >=3.4.0,<4.0.0
